<Object levels="10" textures="1" area="8,569">
    <Levels>
        <Representation level="0" filename="level0.drc" size="11"/>
        <Representation level="1" filename="level1.drc" size="47"/>
        <Representation level="2" filename="level2.drc" size="70"/>
        <Representation level="3" filename="level3.drc" size="90"/>
        <Representation level="4" filename="level4.drc" size="107"/>
        <Representation level="5" filename="level5.drc" size="123"/>
        <Representation level="6" filename="level6.drc" size="138"/>
        <Representation level="7" filename="level7.drc" size="154"/>
        <Representation level="8" filename="level8.drc" size="170"/>
        <Representation level="9" filename="full.drc" size="186"/>
    </Levels>

    <Textures>
        <Representation level="0" filename="model.jpg" size="580"/>
    </Textures>
</Object>